wellets_cli/VERSION
wellets_cli/__init__.py
wellets_cli/__main__.py
wellets_cli/api.py
wellets_cli/auth.py
wellets_cli/base.py
wellets_cli/chart.py
wellets_cli/cli.py
wellets_cli/commands/__init__.py
wellets_cli/commands/accumulation.py
wellets_cli/commands/asset.py
wellets_cli/commands/currency.py
wellets_cli/commands/dashboard.py
wellets_cli/commands/investment.py
wellets_cli/commands/login.py
wellets_cli/commands/portfolio.py
wellets_cli/commands/register.py
wellets_cli/commands/transaction.py
wellets_cli/commands/transfer.py
wellets_cli/commands/wallet.py
wellets_cli/commands/whoami.py
wellets_cli/config.py
wellets_cli/model.py
wellets_cli/prompt.py
wellets_cli/question.py
wellets_cli/util.py
wellets_cli/validator.py
wellets_cli-1.11.0.dist-info/LICENSE
wellets_cli-1.11.0.dist-info/METADATA
wellets_cli-1.11.0.dist-info/WHEEL
wellets_cli-1.11.0.dist-info/entry_points.txt
wellets_cli-1.11.0.dist-info/RECORD
